{
  "indexes": [
    {
      "collectionGroup": "token_invoices",
      "queryScope": "COLLECTION",
      "fields": [
        { "fieldPath": "userId", "order": "ASCENDING" },
        { "fieldPath": "createdAt", "order": "DESCENDING" }
      ]
    },
    {
      "collectionGroup": "token_invoices",
      "queryScope": "COLLECTION",
      "fields": [
        { "fieldPath": "userId", "order": "ASCENDING" },
        { "fieldPath": "type", "order": "ASCENDING" },
        { "fieldPath": "createdAt", "order": "DESCENDING" }
      ]
    },
    {
      "collectionGroup": "bank_transactions",
      "queryScope": "COLLECTION",
      "fields": [
        { "fieldPath": "accountId", "order": "ASCENDING" },
        { "fieldPath": "sequenceNumber", "order": "DESCENDING" }
      ]
    }
  ],
  "fieldOverrides": []
}
